bt1337xearch/__init__.py
bt1337xearch/parser.py
bt1337xearch-0.1.0.dist-info/WHEEL
bt1337xearch-0.1.0.dist-info/entry_points.txt
bt1337xearch-0.1.0.dist-info/METADATA
bt1337xearch-0.1.0.dist-info/RECORD
