Metadata-Version: 2.3
Name: bt1337xearch
Version: 0.1.0
Summary: Better search for 1337x[.]to with basic filters
Author: SimoneFelici
Author-email: SimoneFelici <felicisimone9@gmail.com>
Requires-Dist: scrapling[fetchers]>=0.3.8
Requires-Dist: textual>=6.5.0
Requires-Python: >=3.14
